sage_libs/__init__.py
sage_libs/sage_privacy/__init__.py
sage_libs/sage_privacy/_register.py
sage_libs/sage_privacy/_version.py
sage_libs/sage_privacy/dp/__init__.py
sage_libs/sage_privacy/dp/gaussian.py
sage_libs/sage_privacy/dp/laplace.py
sage_libs/sage_privacy/unlearning/__init__.py
sage_libs/sage_privacy/unlearning/fisher_forgetting.py
sage_libs/sage_privacy/unlearning/gradient_ascent.py
isage_privacy-0.1.0.0.dist-info/METADATA
isage_privacy-0.1.0.0.dist-info/WHEEL
isage_privacy-0.1.0.0.dist-info/top_level.txt
isage_privacy-0.1.0.0.dist-info/RECORD
